{
	"backtrace" : 2,
	"backtraceGraph" : 
	{
		"commands" : 
		[
			"add_custom_target",
			"add_input_files"
		],
		"files" : 
		[
			"/usr/share/cmake-3.16/Modules/CMakeAfbTemplates/cmake/cmake.d/03-macros.cmake",
			"test/afb-test/fixtures/CMakeLists.txt"
		],
		"nodes" : 
		[
			{
				"file" : 1
			},
			{
				"command" : 1,
				"file" : 1,
				"line" : 26,
				"parent" : 0
			},
			{
				"command" : 0,
				"file" : 0,
				"line" : 196,
				"parent" : 1
			}
		]
	},
	"id" : "fixture-files::@f61c24e65c3433d5d598",
	"name" : "fixture-files",
	"paths" : 
	{
		"build" : "test/afb-test/fixtures",
		"source" : "test/afb-test/fixtures"
	},
	"sourceGroups" : 
	[
		{
			"name" : "",
			"sourceIndexes" : 
			[
				0
			]
		},
		{
			"name" : "CMake Rules",
			"sourceIndexes" : 
			[
				1,
				2
			]
		}
	],
	"sources" : 
	[
		{
			"backtrace" : 2,
			"isGenerated" : true,
			"path" : "build/test/afb-test/fixtures/CMakeFiles/fixture-files",
			"sourceGroupIndex" : 0
		},
		{
			"backtrace" : 0,
			"isGenerated" : true,
			"path" : "build/test/afb-test/fixtures/CMakeFiles/fixture-files.rule",
			"sourceGroupIndex" : 1
		},
		{
			"backtrace" : 0,
			"isGenerated" : true,
			"path" : "build/test/afb-test/fixtures/fixture-files.rule",
			"sourceGroupIndex" : 1
		}
	],
	"type" : "UTILITY"
}
